ALU/ALU.v
module ALU( A, B, c_in, control_line, mode_select, out, c_out);

input [7:0] A, B;
input c_in;
input [2:0] control_line;
input mode_select;

output reg c_out;
output reg [7:0] out;

always@(*)
begin
    if(mode_select)
    begin
       case(control_line)
            3'd0 :  {c_out, out} = A + B + c_in;
            3'd1 :  {c_out, out} = A - B - c_in;
            3'd2 :  {c_out, out} = A + 1'b1;
            3'd3 :  {c_out, out} = B + 1'b1;
            3'd4 :  {c_out, out} = A - 1'b1;
            3'd5 :  {c_out, out} = B - 1'b1;
            3'd6 :  begin out = A; c_out = 0; end
            3'd7 :  begin out = B; c_out = 0; end
            default: out  = 8'd0;
       endcase
    end
    else
    begin
       c_out = 0; 
       case(control_line)
            3'd0 :  out = A & B;
            3'd1 :  out = A | B; 
            3'd2 :  out = A ^ B;
	    3'd3 :  out = ~ (A | B);
            3'd4 :  out = A << 2;
            3'd5 :  out = B << 2;
            3'd6 :  out = A >> 2;
            3'd7 :  out = B >> 2;
            default: out  = 8'd0;       
       endcase
    end
end

endmodule

ALU/ALU_tb.v
`include "ALU.v"

module ALU_TB();

reg [7:0] a, b;
reg C_IN;
reg [2:0] CONTROL_LINE;
reg MODE_SELECT;

wire [7:0]OUT;
wire C_OUT;
integer i;
integer j;
//Creating ALU instant
ALU i1
(
    .A(a),
    .B(b),
    .c_in(C_IN),
    .control_line(CONTROL_LINE),
    .mode_select(MODE_SELECT),
    .out(OUT),
    .c_out(C_OUT)
);

initial 
begin
    $dumpfile("ALU_tb.vcd");
    $dumpvars(0, ALU_TB);
end

initial
begin
    a = 8'd2; b = 8'd3; C_IN = 0;
    MODE_SELECT = 0;
    CONTROL_LINE = 3'd0;
    for(i = 0; i < 2; i++)
    begin
    #5  MODE_SELECT = i; CONTROL_LINE = 3'd0;
        for(j = 1; j < 8; j++)
            #5 CONTROL_LINE = j;
    end
    #5  $finish;
end
endmodule

ALU/ALU_tb.vcd
$date
	Fri Jan 21 21:06:13 2022
$end
$version
	Icarus Verilog
$end
$timescale
	1s
$end
$scope module ALU_TB $end
$var wire 8 ! OUT [7:0] $end
$var wire 1 " C_OUT $end
$var reg 3 # CONTROL_LINE [2:0] $end
$var reg 1 $ C_IN $end
$var reg 1 % MODE_SELECT $end
$var reg 8 & a [7:0] $end
$var reg 8 ' b [7:0] $end
$var integer 32 ( i [31:0] $end
$var integer 32 ) j [31:0] $end
$scope module i1 $end
$var wire 8 * A [7:0] $end
$var wire 8 + B [7:0] $end
$var wire 1 $ c_in $end
$var wire 3 , control_line [2:0] $end
$var wire 1 % mode_select $end
$var reg 1 " c_out $end
$var reg 8 - out [7:0] $end
$upscope $end
$upscope $end
$enddefinitions $end
#0
$dumpvars
b10 -
b0 ,
b11 +
b10 *
bx )
b0 (
b11 '
b10 &
0%
0$
b0 #
0"
b10 !
$end
#5
b1 )
#10
b11 !
b11 -
b10 )
b1 #
b1 ,
#15
b1 !
b1 -
b11 )
b10 #
b10 ,
#20
b11111100 !
b11111100 -
b100 )
b11 #
b11 ,
#25
b1000 !
b1000 -
b101 )
b100 #
b100 ,
#30
b1100 !
b1100 -
b110 )
b101 #
b101 ,
#35
b0 !
b0 -
b111 )
b110 #
b110 ,
#40
b1 (
b1000 )
b111 #
b111 ,
#45
b101 !
b101 -
b1 )
b0 #
b0 ,
1%
#50
1"
b11111111 !
b11111111 -
b10 )
b1 #
b1 ,
#55
0"
b11 !
b11 -
b11 )
b10 #
b10 ,
#60
b100 !
b100 -
b100 )
b11 #
b11 ,
#65
b1 !
b1 -
b101 )
b100 #
b100 ,
#70
b10 !
b10 -
b110 )
b101 #
b101 ,
#75
b111 )
b110 #
b110 ,
#80
b11 !
b11 -
b10 (
b1000 )
b111 #
b111 ,
